[
    {
        "word": "Adversary",
        "part_of_speech": "Noun",
        "definition": "One's opponent in a contest, conflict, or dispute.",
        "hindi_meaning": "प्रतिद्वंदी, शत्रु",
        "mnemonic": "Adversary sounds like 'adverse-sary,' indicating someone who is against or opposed to you.",
        "visual_representation": "Picture two chess players facing off against each other, symbolizing adversaries.",
        "example_sentence": "The tennis player prepared to face his longtime adversary in the finals."
    },
    {
        "word": "Bludgeon",
        "part_of_speech": "Noun / Verb",
        "definition": "A thick stick with a heavy end, used as a weapon; to beat someone repeatedly with a bludgeon or other heavy object.",
        "hindi_meaning": "गदा, भारी वस्तु से मारना",
        "mnemonic": "Bludgeon sounds like 'blud-geon,' indicating a blunt, heavy weapon used to hit.",
        "visual_representation": "Picture a club with a heavy end being wielded as a weapon, symbolizing a bludgeon.",
        "example_sentence": "The thief was caught trying to bludgeon the store owner with a metal pipe."
    },
    {
        "word": "Charisma",
        "part_of_speech": "Noun",
        "definition": "Compelling attractiveness or charm that can inspire devotion in others.",
        "hindi_meaning": "करिश्मा, आकर्षण",
        "mnemonic": "Charisma sounds like 'charm-risma,' indicating a natural charm or appeal.",
        "visual_representation": "Imagine a charismatic leader speaking to a crowd, effortlessly inspiring them.",
        "example_sentence": "The politician’s charisma won over the crowd, securing their votes."
    },
    {
        "word": "Deprecate",
        "part_of_speech": "Verb",
        "definition": "To express disapproval of something; to belittle or criticize.",
        "hindi_meaning": "निंदा करना, तिरस्कार करना",
        "mnemonic": "Deprecate sounds like 'depreciate,' indicating lowering or criticizing something.",
        "visual_representation": "Picture someone shaking their head in disapproval, symbolizing deprecation.",
        "example_sentence": "The teacher deprecated the use of slang in formal essays."
    },
    {
        "word": "Entomology",
        "part_of_speech": "Noun",
        "definition": "The scientific study of insects.",
        "hindi_meaning": "कीटविज्ञान",
        "mnemonic": "Entomology sounds like 'ant-omology,' indicating the study of insects like ants.",
        "visual_representation": "Picture a scientist examining insects under a microscope, symbolizing entomology.",
        "example_sentence": "Her passion for insects led her to study entomology at university."
    },
    {
        "word": "Foliage",
        "part_of_speech": "Noun",
        "definition": "Plant leaves, collectively.",
        "hindi_meaning": "पत्ते, हरियाली",
        "mnemonic": "Foliage sounds like 'full-leaf-age,' indicating a collection of leaves.",
        "visual_representation": "Imagine a tree with lush green leaves, symbolizing foliage.",
        "example_sentence": "The fall foliage in the mountains was a spectacular display of red, orange, and yellow."
    },
    {
        "word": "Gruel",
        "part_of_speech": "Noun",
        "definition": "A thin liquid food of oatmeal or other meal boiled in milk or water.",
        "hindi_meaning": "पतली खिचड़ी, पतला दलिया",
        "mnemonic": "Gruel sounds like 'gruel-ing,' as in a basic, often unappetizing food.",
        "visual_representation": "Picture a bowl of thin, watery porridge, symbolizing gruel.",
        "example_sentence": "The orphanage served a small portion of gruel to the children each morning."
    },
    {
        "word": "Hypothetical",
        "part_of_speech": "Adjective / Noun",
        "definition": "Based on or serving as a hypothesis; a supposed or assumed scenario.",
        "hindi_meaning": "काल्पनिक, अनुमानी",
        "mnemonic": "Hypothetical sounds like 'hyper-thetical,' indicating something theoretical or imagined.",
        "visual_representation": "Imagine a thought bubble with a question mark inside, symbolizing a hypothetical situation.",
        "example_sentence": "The professor posed a hypothetical question to stimulate discussion."
    },
    {
        "word": "Incidence",
        "part_of_speech": "Noun",
        "definition": "The occurrence, rate, or frequency of a disease, crime, or something else undesirable.",
        "hindi_meaning": "घटना, प्रकोप",
        "mnemonic": "Incidence sounds like 'in-sid-ence,' indicating how often something happens.",
        "visual_representation": "Picture a graph showing the rise and fall of a disease's incidence in a population.",
        "example_sentence": "The incidence of flu cases tends to increase in the winter months."
    },
    {
        "word": "Labyrinth",
        "part_of_speech": "Noun",
        "definition": "A complicated irregular network of passages or paths in which it is difficult to find one’s way; a maze.",
        "hindi_meaning": "भूलभुलैया, जटिल मार्ग",
        "mnemonic": "Labyrinth sounds like 'lab-rinth,' indicating a complex, maze-like structure.",
        "visual_representation": "Picture a maze with twisting and turning paths, symbolizing a labyrinth.",
        "example_sentence": "The ancient castle had a labyrinth of secret passages."
    },
    {
        "word": "Minute",
        "part_of_speech": "Adjective",
        "definition": "Extremely small in size, amount, or degree; of minor importance.",
        "hindi_meaning": "सूक्ष्म, बहुत छोटा",
        "mnemonic": "Minute sounds like 'my-newt,' indicating something very small or detailed.",
        "visual_representation": "Imagine looking at a tiny detail through a magnifying glass, symbolizing something minute.",
        "example_sentence": "The scientist examined the minute particles under a powerful microscope."
    },
    {
        "word": "Natty",
        "part_of_speech": "Adjective",
        "definition": "(Especially of a person or an article of clothing) smart and fashionable.",
        "hindi_meaning": "सजीला, साफ-सुथरा",
        "mnemonic": "Natty sounds like 'neat-ty,' indicating someone who is neatly dressed or fashionable.",
        "visual_representation": "Picture a person in a well-tailored suit, looking sharp and stylish, symbolizing natty.",
        "example_sentence": "He always looked natty in his crisp, tailored suits."
    },
    {
        "word": "Odium",
        "part_of_speech": "Noun",
        "definition": "General or widespread hatred or disgust incurred by someone as a result of their actions.",
        "hindi_meaning": "घृणा, नफ़रत",
        "mnemonic": "Odium sounds like 'odium-ous,' indicating something that inspires widespread hatred or disgust.",
        "visual_representation": "Picture a public figure surrounded by angry protesters, symbolizing odium.",
        "example_sentence": "The corrupt politician faced public odium after the scandal was exposed."
    },
    {
        "word": "Permeate",
        "part_of_speech": "Verb",
        "definition": "To spread throughout something; to pervade.",
        "hindi_meaning": "फैलना, व्याप्त होना",
        "mnemonic": "Permeate sounds like 'per-meet,' as if something is spreading or meeting throughout an area.",
        "visual_representation": "Imagine a drop of ink spreading through water, symbolizing permeation.",
        "example_sentence": "The smell of freshly baked bread permeated the entire house."
    },
    {
        "word": "Remunerative",
        "part_of_speech": "Adjective",
        "definition": "Financially rewarding; lucrative.",
        "hindi_meaning": "लाभदायक, मुनाफे वाला",
        "mnemonic": "Remunerative sounds like 're-mun-erative,' indicating something that brings in money or rewards.",
        "visual_representation": "Picture someone receiving a stack of cash as a reward for their work, symbolizing remunerative benefits.",
        "example_sentence": "He left his job for a more remunerative position in another company."
    },
    {
        "word": "Shimmer",
        "part_of_speech": "Verb / Noun",
        "definition": "To shine with a soft, slightly wavering light; a faint or soft light.",
        "hindi_meaning": "झिलमिलाना, मद्धिम चमक",
        "mnemonic": "Shimmer sounds like 'shy-mirror,' indicating a soft, wavering light like a reflection.",
        "visual_representation": "Imagine a calm lake reflecting the moonlight with a gentle, shimmering effect.",
        "example_sentence": "The stars shimmered in the clear night sky."
    },
    {
        "word": "Transmute",
        "part_of_speech": "Verb",
        "definition": "To change in form, nature, or substance.",
        "hindi_meaning": "रूपांतरण करना, बदलना",
        "mnemonic": "Transmute sounds like 'transform-mute,' indicating a complete change from one form to another.",
        "visual_representation": "Picture a wizard turning lead into gold, symbolizing transmutation.",
        "example_sentence": "The alchemist sought to transmute base metals into gold."
    },
    {
        "word": "Unassailable",
        "part_of_speech": "Adjective",
        "definition": "Unable to be attacked, questioned, or defeated.",
        "hindi_meaning": "अभेद्य, अजेय",
        "mnemonic": "Unassailable sounds like 'un-assault-able,' indicating something that cannot be attacked or defeated.",
        "visual_representation": "Imagine a fortress with walls so high and strong that it is unassailable.",
        "example_sentence": "The lawyer presented an unassailable argument that left no room for doubt."
    },
    {
        "word": "Vent",
        "part_of_speech": "Verb / Noun",
        "definition": "To release or express (a strong emotion, energy, etc.); an opening that allows air, gas, or liquid to pass out of or into a confined space.",
        "hindi_meaning": "निकालना, निकासी",
        "mnemonic": "Vent sounds like 'ventilation,' indicating releasing or letting something out.",
        "visual_representation": "Picture someone angrily venting their frustrations to a friend, symbolizing venting.",
        "example_sentence": "After a long day at work, he needed to vent his frustrations to someone."
    },
    {
        "word": "Windfall",
        "part_of_speech": "Noun",
        "definition": "An unexpected gain or piece of good fortune, typically one involving money.",
        "hindi_meaning": "आकस्मिक लाभ, अचानक प्राप्ति",
        "mnemonic": "Windfall sounds like 'wind-fall,' as if fortune falls into your lap like a gust of wind.",
        "visual_representation": "Imagine a pile of money falling from the sky, symbolizing a windfall.",
        "example_sentence": "Winning the lottery was an incredible windfall for the family."
    }
]
